Metadata-Version: 1.1
Name: django-tables2-reports
Version: 0.1.3
Summary: With django-tables2-reports you can get a report (CSV, XLS) of any django-tables2 with minimal changes to your project
Home-page: https://github.com/goinnn/django-tables2-reports
Author: Pablo Martin
Author-email: goinnn@gmail.com
License: LGPL 3
Keywords: django,tables,django-tables2,reports,CSV,XLS
Platform: UNKNOWN
Classifier: Development Status :: 4 - Beta
Classifier: Framework :: Django
Classifier: License :: OSI Approved :: GNU Library or Lesser General Public License (LGPL)
Classifier: Programming Language :: Python :: 2
Classifier: Programming Language :: Python :: 3
